{"name":"test002","id":"in.reqres.reqresCURD.ReqresCURD:test002","testCaseName":"in.reqres.reqresCURD.ReqresCURD","testSteps":[{"number":1,"description":"Getting the User information with Id: \u003cnull\u003e","duration":8,"startTime":"2022-06-06T23:11:45.539+01:00[Europe/London]","exception":{"errorType":"java.lang.IllegalArgumentException","message":"parameterValue cannot be null","stackTrace":[{"declaringClass":"io.restassured.internal.assertion.AssertParameter","methodName":"notNull","fileName":"AssertParameter.groovy","lineNumber":26},{"declaringClass":"io.restassured.internal.RequestSpecificationImpl","methodName":"pathParameter","fileName":"RequestSpecificationImpl.groovy","lineNumber":560},{"declaringClass":"groovy.lang.MetaMethod","methodName":"doMethodInvoke","fileName":"MetaMethod.java","lineNumber":325},{"declaringClass":"groovy.lang.MetaClassImpl","methodName":"invokeMethod","fileName":"MetaClassImpl.java","lineNumber":1213},{"declaringClass":"groovy.lang.MetaClassImpl","methodName":"invokeMethod","fileName":"MetaClassImpl.java","lineNumber":1022},{"declaringClass":"groovy.lang.MetaClassImpl","methodName":"invokeMethod","fileName":"MetaClassImpl.java","lineNumber":810},{"declaringClass":"io.restassured.internal.RequestSpecificationImpl","methodName":"invokeMethod","fileName":"RequestSpecificationImpl.groovy","lineNumber":-1},{"declaringClass":"io.restassured.internal.RequestSpecificationImpl","methodName":"pathParam","fileName":"RequestSpecificationImpl.groovy","lineNumber":578},{"declaringClass":"net.serenitybdd.rest.decorators.request.RequestSpecificationParametersConfigurations","methodName":"pathParam","fileName":"RequestSpecificationParametersConfigurations.java","lineNumber":188},{"declaringClass":"net.serenitybdd.rest.decorators.request.RequestSpecificationDecorated","methodName":"pathParam","fileName":"RequestSpecificationDecorated.java","lineNumber":27},{"declaringClass":"in.reqres.reqresinfo.ReqresStep","methodName":"getUserInfoByName","fileName":"ReqresStep.java","lineNumber":33},{"declaringClass":"in.reqres.reqresCURD.ReqresCURD","methodName":"test002","fileName":"ReqresCURD.java","lineNumber":44}]},"result":"ERROR","precondition":false}],"userStory":{"id":"in.reqres.reqresCURD.ReqresCURD","storyName":"Reqres CURD","storyClassName":"in.reqres.reqresCURD.ReqresCURD","path":"in.reqres.reqresCURD","type":"story"},"featureTag":{"name":"Reqres CURD/Reqres CURD","type":"story"},"title":"Verify that new user is added","tags":[{"name":"Reqres CURD/Reqres CURD","type":"story"}],"startTime":"2022-06-06T23:11:45.538+01:00[Europe/London]","duration":18,"testFailureCause":{"errorType":"java.lang.IllegalArgumentException","message":"parameterValue cannot be null","stackTrace":[{"declaringClass":"io.restassured.internal.assertion.AssertParameter","methodName":"notNull","fileName":"AssertParameter.groovy","lineNumber":26},{"declaringClass":"io.restassured.internal.RequestSpecificationImpl","methodName":"pathParameter","fileName":"RequestSpecificationImpl.groovy","lineNumber":560},{"declaringClass":"groovy.lang.MetaMethod","methodName":"doMethodInvoke","fileName":"MetaMethod.java","lineNumber":325},{"declaringClass":"groovy.lang.MetaClassImpl","methodName":"invokeMethod","fileName":"MetaClassImpl.java","lineNumber":1213},{"declaringClass":"groovy.lang.MetaClassImpl","methodName":"invokeMethod","fileName":"MetaClassImpl.java","lineNumber":1022},{"declaringClass":"groovy.lang.MetaClassImpl","methodName":"invokeMethod","fileName":"MetaClassImpl.java","lineNumber":810},{"declaringClass":"io.restassured.internal.RequestSpecificationImpl","methodName":"invokeMethod","fileName":"RequestSpecificationImpl.groovy","lineNumber":-1},{"declaringClass":"io.restassured.internal.RequestSpecificationImpl","methodName":"pathParam","fileName":"RequestSpecificationImpl.groovy","lineNumber":578},{"declaringClass":"net.serenitybdd.rest.decorators.request.RequestSpecificationParametersConfigurations","methodName":"pathParam","fileName":"RequestSpecificationParametersConfigurations.java","lineNumber":188},{"declaringClass":"net.serenitybdd.rest.decorators.request.RequestSpecificationDecorated","methodName":"pathParam","fileName":"RequestSpecificationDecorated.java","lineNumber":27},{"declaringClass":"in.reqres.reqresinfo.ReqresStep","methodName":"getUserInfoByName","fileName":"ReqresStep.java","lineNumber":33},{"declaringClass":"in.reqres.reqresCURD.ReqresCURD","methodName":"test002","fileName":"ReqresCURD.java","lineNumber":44}]},"testFailureClassname":"java.lang.IllegalArgumentException","testFailureMessage":"parameterValue cannot be null","testFailureSummary":"ERROR;java.lang.IllegalArgumentException;parameterValue cannot be null;AssertParameter.groovy","projectKey":"","annotatedResult":"ERROR","manual":false,"testSource":"JUnit","result":"ERROR"}